{"time_used": 106, "request_id": "1664686025,e5da80ab-8595-407e-b618-a4c9acd69e59", "faces": [{"landmark": {"mouth_upper_lip_left_contour2": {"y": 199, "x": 263}, "mouth_upper_lip_top": {"y": 197, "x": 281}, "mouth_upper_lip_left_contour1": {"y": 195, "x": 275}, "left_eye_upper_left_quarter": {"y": 126, "x": 238}, "left_eyebrow_lower_middle": {"y": 119, "x": 243}, "mouth_upper_lip_left_contour3": {"y": 202, "x": 267}, "right_eye_top": {"y": 123, "x": 314}, "left_eye_bottom": {"y": 133, "x": 246}, "right_eyebrow_lower_left_quarter": {"y": 118, "x": 306}, "right_eye_pupil": {"y": 128, "x": 315}, "mouth_lower_lip_right_contour1": {"y": 202, "x": 295}, "mouth_lower_lip_right_contour3": {"y": 210, "x": 292}, "mouth_lower_lip_right_contour2": {"y": 207, "x": 302}, "contour_chin": {"y": 257, "x": 283}, "contour_left9": {"y": 254, "x": 263}, "left_eye_lower_right_quarter": {"y": 132, "x": 253}, "mouth_lower_lip_top": {"y": 203, "x": 281}, "right_eyebrow_upper_middle": {"y": 108, "x": 318}, "left_eyebrow_left_corner": {"y": 123, "x": 221}, "right_eye_bottom": {"y": 132, "x": 315}, "contour_left7": {"y": 232, "x": 233}, "contour_left6": {"y": 218, "x": 223}, "contour_left5": {"y": 202, "x": 215}, "contour_left4": {"y": 185, "x": 210}, "contour_left3": {"y": 167, "x": 208}, "contour_left2": {"y": 149, "x": 207}, "contour_left1": {"y": 131, "x": 208}, "left_eye_lower_left_quarter": {"y": 133, "x": 239}, "contour_right1": {"y": 129, "x": 352}, "contour_right3": {"y": 164, "x": 354}, "contour_right2": {"y": 147, "x": 354}, "mouth_left_corner": {"y": 203, "x": 252}, "contour_right4": {"y": 182, "x": 352}, "contour_right7": {"y": 232, "x": 332}, "right_eyebrow_left_corner": {"y": 118, "x": 295}, "nose_right": {"y": 171, "x": 302}, "nose_tip": {"y": 163, "x": 281}, "contour_right5": {"y": 200, "x": 349}, "nose_contour_lower_middle": {"y": 178, "x": 280}, "left_eyebrow_lower_left_quarter": {"y": 120, "x": 232}, "mouth_lower_lip_left_contour3": {"y": 210, "x": 270}, "right_eye_right_corner": {"y": 128, "x": 328}, "right_eye_lower_right_quarter": {"y": 131, "x": 322}, "mouth_upper_lip_right_contour2": {"y": 198, "x": 299}, "right_eyebrow_lower_right_quarter": {"y": 118, "x": 328}, "left_eye_left_corner": {"y": 132, "x": 232}, "mouth_right_corner": {"y": 202, "x": 310}, "mouth_upper_lip_right_contour3": {"y": 202, "x": 295}, "right_eye_lower_left_quarter": {"y": 132, "x": 307}, "left_eyebrow_right_corner": {"y": 117, "x": 264}, "left_eyebrow_lower_right_quarter": {"y": 118, "x": 254}, "right_eye_center": {"y": 129, "x": 314}, "nose_left": {"y": 170, "x": 260}, "mouth_lower_lip_left_contour1": {"y": 203, "x": 267}, "left_eye_upper_right_quarter": {"y": 126, "x": 254}, "right_eyebrow_lower_middle": {"y": 117, "x": 317}, "left_eye_top": {"y": 124, "x": 246}, "left_eye_center": {"y": 130, "x": 246}, "contour_left8": {"y": 244, "x": 247}, "contour_right9": {"y": 254, "x": 303}, "right_eye_left_corner": {"y": 130, "x": 300}, "mouth_lower_lip_bottom": {"y": 211, "x": 281}, "left_eyebrow_upper_left_quarter": {"y": 114, "x": 231}, "left_eye_pupil": {"y": 128, "x": 244}, "right_eyebrow_upper_left_quarter": {"y": 110, "x": 304}, "contour_right8": {"y": 244, "x": 320}, "right_eyebrow_right_corner": {"y": 121, "x": 338}, "right_eye_upper_left_quarter": {"y": 126, "x": 306}, "left_eyebrow_upper_middle": {"y": 110, "x": 242}, "right_eyebrow_upper_right_quarter": {"y": 112, "x": 329}, "nose_contour_left1": {"y": 130, "x": 270}, "nose_contour_left2": {"y": 157, "x": 265}, "mouth_upper_lip_right_contour1": {"y": 195, "x": 288}, "nose_contour_right1": {"y": 130, "x": 291}, "nose_contour_right2": {"y": 157, "x": 297}, "mouth_lower_lip_left_contour2": {"y": 208, "x": 261}, "contour_right6": {"y": 217, "x": 342}, "nose_contour_right3": {"y": 176, "x": 292}, "nose_contour_left3": {"y": 175, "x": 270}, "left_eye_right_corner": {"y": 131, "x": 260}, "left_eyebrow_upper_right_quarter": {"y": 111, "x": 255}, "right_eye_upper_right_quarter": {"y": 125, "x": 322}, "mouth_upper_lip_bottom": {"y": 202, "x": 281}}, "attributes": {"emotion": {"sadness": 0.006, "neutral": 99.861, "disgust": 0.006, "anger": 0.0, "surprise": 0.0, "fear": 0.0, "happiness": 0.126}, "beauty": {"female_score": 63.474, "male_score": 54.151}, "gender": {"value": "Male"}, "age": {"value": 38}, "mouthstatus": {"close": 99.977, "surgical_mask_or_respirator": 0.0, "open": 0.0, "other_occlusion": 0.023}, "glass": {"value": "None"}, "skinstatus": {"dark_circle": 99.625, "stain": 99.828, "acne": 99.037, "health": 0.275}, "headpose": {"yaw_angle": 2.9155736, "pitch_angle": 3.3565137, "roll_angle": -0.42777947}, "blur": {"blurness": {"threshold": 50.0, "value": 1.148}, "motionblur": {"threshold": 50.0, "value": 1.148}, "gaussianblur": {"threshold": 50.0, "value": 1.148}}, "smile": {"threshold": 50.0, "value": 0.071}, "eyestatus": {"left_eye_status": {"normal_glass_eye_open": 0.018, "no_glass_eye_close": 0.0, "occlusion": 0.0, "no_glass_eye_open": 99.982, "normal_glass_eye_close": 0.0, "dark_glasses": 0.0}, "right_eye_status": {"normal_glass_eye_open": 0.0, "no_glass_eye_close": 0.0, "occlusion": 0.0, "no_glass_eye_open": 100.0, "normal_glass_eye_close": 0.0, "dark_glasses": 0.0}}, "facequality": {"threshold": 70.1, "value": 92.416}, "eyegaze": {"right_eye_gaze": {"position_x_coordinate": 0.537, "vector_z_component": 0.992, "vector_x_component": 0.014, "vector_y_component": -0.128, "position_y_coordinate": 0.451}, "left_eye_gaze": {"position_x_coordinate": 0.472, "vector_z_component": 0.886, "vector_x_component": -0.131, "vector_y_component": -0.444, "position_y_coordinate": 0.404}}}, "face_rectangle": {"width": 150, "top": 108, "left": 205, "height": 150}, "face_token": "8d8fe8062a82848983a30620c5f1de52"}]}