{"time_used": 313, "request_id": "1664686042,b8c8ff13-0985-47dd-b4d7-13b3da63e175", "faces": [{"landmark": {"mouth_upper_lip_left_contour2": {"y": 2104, "x": 939}, "mouth_upper_lip_top": {"y": 2109, "x": 1098}, "mouth_upper_lip_left_contour1": {"y": 2091, "x": 1039}, "left_eye_upper_left_quarter": {"y": 1364, "x": 722}, "left_eyebrow_lower_middle": {"y": 1196, "x": 765}, "mouth_upper_lip_left_contour3": {"y": 2140, "x": 969}, "right_eye_top": {"y": 1418, "x": 1457}, "left_eye_bottom": {"y": 1470, "x": 788}, "right_eyebrow_lower_left_quarter": {"y": 1262, "x": 1387}, "right_eye_pupil": {"y": 1463, "x": 1457}, "mouth_lower_lip_right_contour1": {"y": 2172, "x": 1225}, "mouth_lower_lip_right_contour3": {"y": 2241, "x": 1194}, "mouth_lower_lip_right_contour2": {"y": 2211, "x": 1283}, "contour_chin": {"y": 2591, "x": 1078}, "contour_left9": {"y": 2537, "x": 919}, "left_eye_lower_right_quarter": {"y": 1463, "x": 869}, "mouth_lower_lip_top": {"y": 2168, "x": 1095}, "right_eyebrow_upper_middle": {"y": 1164, "x": 1495}, "left_eyebrow_left_corner": {"y": 1215, "x": 589}, "right_eye_bottom": {"y": 1522, "x": 1456}, "contour_left7": {"y": 2310, "x": 711}, "contour_left6": {"y": 2178, "x": 638}, "contour_left5": {"y": 2032, "x": 589}, "contour_left4": {"y": 1878, "x": 563}, "contour_left3": {"y": 1725, "x": 545}, "contour_left2": {"y": 1572, "x": 536}, "contour_left1": {"y": 1418, "x": 541}, "left_eye_lower_left_quarter": {"y": 1453, "x": 717}, "contour_right1": {"y": 1494, "x": 1787}, "contour_right3": {"y": 1806, "x": 1750}, "contour_right2": {"y": 1651, "x": 1775}, "mouth_left_corner": {"y": 2121, "x": 840}, "contour_right4": {"y": 1961, "x": 1716}, "contour_right7": {"y": 2382, "x": 1507}, "right_eyebrow_left_corner": {"y": 1256, "x": 1278}, "nose_right": {"y": 1868, "x": 1320}, "nose_tip": {"y": 1822, "x": 1093}, "contour_right5": {"y": 2116, "x": 1670}, "nose_contour_lower_middle": {"y": 1948, "x": 1106}, "left_eyebrow_lower_left_quarter": {"y": 1199, "x": 673}, "mouth_lower_lip_left_contour3": {"y": 2224, "x": 985}, "right_eye_right_corner": {"y": 1491, "x": 1591}, "right_eye_lower_right_quarter": {"y": 1516, "x": 1531}, "mouth_upper_lip_right_contour2": {"y": 2130, "x": 1259}, "right_eyebrow_lower_right_quarter": {"y": 1266, "x": 1592}, "left_eye_left_corner": {"y": 1417, "x": 668}, "mouth_right_corner": {"y": 2162, "x": 1363}, "mouth_upper_lip_right_contour3": {"y": 2160, "x": 1225}, "right_eye_lower_left_quarter": {"y": 1506, "x": 1379}, "left_eyebrow_right_corner": {"y": 1220, "x": 969}, "left_eyebrow_lower_right_quarter": {"y": 1211, "x": 866}, "right_eye_center": {"y": 1479, "x": 1454}, "nose_left": {"y": 1848, "x": 910}, "mouth_lower_lip_left_contour1": {"y": 2150, "x": 969}, "left_eye_upper_right_quarter": {"y": 1382, "x": 883}, "right_eyebrow_lower_middle": {"y": 1258, "x": 1492}, "left_eye_top": {"y": 1348, "x": 802}, "left_eye_center": {"y": 1421, "x": 801}, "contour_left8": {"y": 2431, "x": 806}, "contour_right9": {"y": 2569, "x": 1250}, "right_eye_left_corner": {"y": 1486, "x": 1311}, "mouth_lower_lip_bottom": {"y": 2246, "x": 1088}, "left_eyebrow_upper_left_quarter": {"y": 1118, "x": 657}, "left_eye_pupil": {"y": 1411, "x": 804}, "right_eyebrow_upper_left_quarter": {"y": 1182, "x": 1373}, "contour_right8": {"y": 2487, "x": 1389}, "right_eyebrow_right_corner": {"y": 1276, "x": 1687}, "right_eye_upper_left_quarter": {"y": 1433, "x": 1376}, "left_eyebrow_upper_middle": {"y": 1091, "x": 769}, "right_eyebrow_upper_right_quarter": {"y": 1192, "x": 1611}, "nose_contour_left1": {"y": 1468, "x": 1014}, "nose_contour_left2": {"y": 1735, "x": 952}, "mouth_upper_lip_right_contour1": {"y": 2100, "x": 1158}, "nose_contour_right1": {"y": 1477, "x": 1239}, "nose_contour_right2": {"y": 1749, "x": 1278}, "mouth_lower_lip_left_contour2": {"y": 2180, "x": 906}, "contour_right6": {"y": 2259, "x": 1602}, "nose_contour_right3": {"y": 1921, "x": 1221}, "nose_contour_left3": {"y": 1909, "x": 997}, "left_eye_right_corner": {"y": 1448, "x": 944}, "left_eyebrow_upper_right_quarter": {"y": 1126, "x": 889}, "right_eye_upper_right_quarter": {"y": 1441, "x": 1534}, "mouth_upper_lip_bottom": {"y": 2157, "x": 1095}}, "attributes": {"emotion": {"sadness": 0.022, "neutral": 6.083, "disgust": 1.708, "anger": 2.461, "surprise": 29.866, "fear": 0.022, "happiness": 59.837}, "beauty": {"female_score": 66.271, "male_score": 67.467}, "gender": {"value": "Male"}, "age": {"value": 19}, "mouthstatus": {"close": 100.0, "surgical_mask_or_respirator": 0.0, "open": 0.0, "other_occlusion": 0.0}, "glass": {"value": "Normal"}, "skinstatus": {"dark_circle": 1.498, "stain": 6.233, "acne": 14.588, "health": 6.997}, "headpose": {"yaw_angle": 6.5789504, "pitch_angle": 4.9546514, "roll_angle": 5.508749}, "blur": {"blurness": {"threshold": 50.0, "value": 0.363}, "motionblur": {"threshold": 50.0, "value": 0.363}, "gaussianblur": {"threshold": 50.0, "value": 0.363}}, "smile": {"threshold": 50.0, "value": 34.15}, "eyestatus": {"left_eye_status": {"normal_glass_eye_open": 74.254, "no_glass_eye_close": 0.0, "occlusion": 0.004, "no_glass_eye_open": 0.625, "normal_glass_eye_close": 0.0, "dark_glasses": 25.117}, "right_eye_status": {"normal_glass_eye_open": 99.262, "no_glass_eye_close": 0.0, "occlusion": 0.001, "no_glass_eye_open": 0.464, "normal_glass_eye_close": 0.0, "dark_glasses": 0.273}}, "facequality": {"threshold": 70.1, "value": 87.878}, "eyegaze": {"right_eye_gaze": {"position_x_coordinate": 0.484, "vector_z_component": 0.977, "vector_x_component": -0.059, "vector_y_component": 0.203, "position_y_coordinate": 0.473}, "left_eye_gaze": {"position_x_coordinate": 0.495, "vector_z_component": 0.973, "vector_x_component": 0.046, "vector_y_component": 0.225, "position_y_coordinate": 0.457}}}, "face_rectangle": {"width": 1470, "top": 1122, "left": 397, "height": 1470}, "face_token": "d1649c3e5a1f26bb85f7c1af2ad65937"}]}