{"time_used": 70, "request_id": "1664686114,b01f93a6-dce2-4bb4-a9cf-822057c520a4", "faces": [{"landmark": {"mouth_upper_lip_left_contour2": {"y": 136, "x": 71}, "mouth_upper_lip_top": {"y": 133, "x": 83}, "mouth_upper_lip_left_contour1": {"y": 133, "x": 79}, "left_eye_upper_left_quarter": {"y": 97, "x": 55}, "left_eyebrow_lower_middle": {"y": 84, "x": 55}, "mouth_upper_lip_left_contour3": {"y": 139, "x": 75}, "right_eye_top": {"y": 90, "x": 102}, "left_eye_bottom": {"y": 103, "x": 60}, "right_eyebrow_lower_left_quarter": {"y": 81, "x": 98}, "right_eye_pupil": {"y": 94, "x": 102}, "mouth_lower_lip_right_contour1": {"y": 139, "x": 94}, "mouth_lower_lip_right_contour3": {"y": 148, "x": 93}, "mouth_lower_lip_right_contour2": {"y": 143, "x": 99}, "contour_chin": {"y": 172, "x": 88}, "contour_left9": {"y": 171, "x": 76}, "left_eye_lower_right_quarter": {"y": 101, "x": 65}, "mouth_lower_lip_top": {"y": 140, "x": 84}, "right_eyebrow_upper_middle": {"y": 76, "x": 106}, "left_eyebrow_left_corner": {"y": 92, "x": 44}, "right_eye_bottom": {"y": 98, "x": 103}, "contour_left7": {"y": 160, "x": 57}, "contour_left6": {"y": 152, "x": 51}, "contour_left5": {"y": 143, "x": 46}, "contour_left4": {"y": 132, "x": 43}, "contour_left3": {"y": 122, "x": 40}, "contour_left2": {"y": 112, "x": 38}, "contour_left1": {"y": 101, "x": 37}, "left_eye_lower_left_quarter": {"y": 102, "x": 55}, "contour_right1": {"y": 93, "x": 127}, "contour_right3": {"y": 114, "x": 129}, "contour_right2": {"y": 103, "x": 128}, "mouth_left_corner": {"y": 142, "x": 66}, "contour_right4": {"y": 125, "x": 128}, "contour_right7": {"y": 155, "x": 117}, "right_eyebrow_left_corner": {"y": 81, "x": 90}, "nose_right": {"y": 117, "x": 99}, "nose_tip": {"y": 116, "x": 83}, "contour_right5": {"y": 136, "x": 127}, "nose_contour_lower_middle": {"y": 124, "x": 84}, "left_eyebrow_lower_left_quarter": {"y": 87, "x": 49}, "mouth_lower_lip_left_contour3": {"y": 149, "x": 77}, "right_eye_right_corner": {"y": 94, "x": 111}, "right_eye_lower_right_quarter": {"y": 97, "x": 108}, "mouth_upper_lip_right_contour2": {"y": 134, "x": 96}, "right_eyebrow_lower_right_quarter": {"y": 81, "x": 112}, "left_eye_left_corner": {"y": 101, "x": 51}, "mouth_right_corner": {"y": 138, "x": 104}, "mouth_upper_lip_right_contour3": {"y": 138, "x": 94}, "right_eye_lower_left_quarter": {"y": 98, "x": 97}, "left_eyebrow_right_corner": {"y": 83, "x": 70}, "left_eyebrow_lower_right_quarter": {"y": 83, "x": 63}, "right_eye_center": {"y": 95, "x": 102}, "nose_left": {"y": 120, "x": 68}, "mouth_lower_lip_left_contour1": {"y": 141, "x": 75}, "left_eye_upper_right_quarter": {"y": 96, "x": 65}, "right_eyebrow_lower_middle": {"y": 80, "x": 105}, "left_eye_top": {"y": 95, "x": 60}, "left_eye_center": {"y": 99, "x": 60}, "contour_left8": {"y": 167, "x": 66}, "contour_right9": {"y": 169, "x": 99}, "right_eye_left_corner": {"y": 96, "x": 92}, "mouth_lower_lip_bottom": {"y": 149, "x": 85}, "left_eyebrow_upper_left_quarter": {"y": 84, "x": 47}, "left_eye_pupil": {"y": 99, "x": 60}, "right_eyebrow_upper_left_quarter": {"y": 76, "x": 97}, "contour_right8": {"y": 163, "x": 109}, "right_eyebrow_right_corner": {"y": 84, "x": 119}, "right_eye_upper_left_quarter": {"y": 92, "x": 96}, "left_eyebrow_upper_middle": {"y": 80, "x": 54}, "right_eyebrow_upper_right_quarter": {"y": 78, "x": 113}, "nose_contour_left1": {"y": 100, "x": 74}, "nose_contour_left2": {"y": 113, "x": 72}, "mouth_upper_lip_right_contour1": {"y": 132, "x": 88}, "nose_contour_right1": {"y": 98, "x": 90}, "nose_contour_right2": {"y": 110, "x": 94}, "mouth_lower_lip_left_contour2": {"y": 146, "x": 71}, "contour_right6": {"y": 146, "x": 123}, "nose_contour_right3": {"y": 121, "x": 92}, "nose_contour_left3": {"y": 123, "x": 76}, "left_eye_right_corner": {"y": 99, "x": 70}, "left_eyebrow_upper_right_quarter": {"y": 79, "x": 63}, "right_eye_upper_right_quarter": {"y": 91, "x": 108}, "mouth_upper_lip_bottom": {"y": 139, "x": 84}}, "attributes": {"emotion": {"sadness": 0.007, "neutral": 0.177, "disgust": 0.012, "anger": 0.011, "surprise": 94.458, "fear": 5.329, "happiness": 0.007}, "beauty": {"female_score": 34.934, "male_score": 30.201}, "gender": {"value": "Male"}, "age": {"value": 24}, "mouthstatus": {"close": 0.087, "surgical_mask_or_respirator": 0.0, "open": 99.913, "other_occlusion": 0.0}, "glass": {"value": "None"}, "skinstatus": {"dark_circle": 5.029, "stain": 2.123, "acne": 5.346, "health": 9.076}, "headpose": {"yaw_angle": 0.23451453, "pitch_angle": 1.6141512, "roll_angle": -6.4820805}, "blur": {"blurness": {"threshold": 50.0, "value": 1.712}, "motionblur": {"threshold": 50.0, "value": 1.712}, "gaussianblur": {"threshold": 50.0, "value": 1.712}}, "smile": {"threshold": 50.0, "value": 9.928}, "eyestatus": {"left_eye_status": {"normal_glass_eye_open": 24.511, "no_glass_eye_close": 0.0, "occlusion": 0.001, "no_glass_eye_open": 75.488, "normal_glass_eye_close": 0.0, "dark_glasses": 0.0}, "right_eye_status": {"normal_glass_eye_open": 3.002, "no_glass_eye_close": 0.0, "occlusion": 0.002, "no_glass_eye_open": 96.992, "normal_glass_eye_close": 0.0, "dark_glasses": 0.003}}, "facequality": {"threshold": 70.1, "value": 94.282}, "eyegaze": {"right_eye_gaze": {"position_x_coordinate": 0.506, "vector_z_component": 0.971, "vector_x_component": 0.194, "vector_y_component": 0.142, "position_y_coordinate": 0.473}, "left_eye_gaze": {"position_x_coordinate": 0.482, "vector_z_component": 0.995, "vector_x_component": -0.007, "vector_y_component": -0.101, "position_y_coordinate": 0.418}}}, "face_rectangle": {"width": 95, "top": 76, "left": 37, "height": 95}, "face_token": "649143fdfd78c9a22c2f084f5168ad8c"}]}